{
  "A": {
	"title":"",
	"underTitle":"",
	"date":"",
	"icon":"fa fa-user",
    "summary": ""
  },
  "B": {
    "title":"",
	"underTitle":"",
	"date":"",
	"icon":"",
    "summary": ""
  },
  "C": {
    "title":"",
	"underTitle":"",
	"date":"",
	"icon":"",
    "summary": ""
  },
  "D": {
    "title":"",
	"underTitle":"",
	"date":"",
	"icon":"",
    "summary": ""
  },
  "E": {
    "title":"",
	"underTitle":"",
	"date":"",
	"icon":"",
    "summary": ""
  },
  "F": {
    "title":"",
	"underTitle":"",
	"date":"",
	"icon":"",
    "summary": ""
  }
}